{
  "name": "Itinfracampusmaster",
  "options": {
    "idInjection": false,
    "mysql": {
      "schema": "ItInfrastructure",
      "table": "ItInfraCampusMaster"
    }
  },
  "properties": {
    "id": {
      "type": "Number",
      "id": 1,
      "required": true,
      "length": null,
      "precision": 10,
      "scale": 0,
      "mysql": {
        "columnName": "id",
        "dataType": "int",
        "dataLength": null,
        "dataPrecision": 10,
        "dataScale": 0,
        "nullable": "N"
      }
    },
    "campusName": {
      "type": "String",
      "required": false,
      "length": 20,
      "precision": null,
      "scale": null,
      "mysql": {
        "columnName": "campus_name",
        "dataType": "varchar",
        "dataLength": 20,
        "dataPrecision": null,
        "dataScale": null,
        "nullable": "Y"
      }
    },
    "campusIncharge": {
      "type": "String",
      "required": false,
      "length": 50,
      "precision": null,
      "scale": null,
      "mysql": {
        "columnName": "campus_incharge",
        "dataType": "varchar",
        "dataLength": 30,
        "dataPrecision": null,
        "dataScale": null,
        "nullable": "Y"
      }
    },
    "campusCity": {
      "type": "String",
      "required": false,
      "length": 30,
      "precision": null,
      "scale": null,
      "mysql": {
        "columnName": "campus_city",
        "dataType": "varchar",
        "dataLength": 30,
        "dataPrecision": null,
        "dataScale": null,
        "nullable": "Y"
      }
    },
    "campusAddress": {
      "type": "String",
      "required": false,
      "length": 100,
      "precision": null,
      "scale": null,
      "mysql": {
        "columnName": "campus_address",
        "dataType": "varchar",
        "dataLength": 100,
        "dataPrecision": null,
        "dataScale": null,
        "nullable": "Y"
      }
    },
    "campusPhone": {
      "type": "String",
      "required": false,
      "length": 60,
      "precision": null,
      "scale": null,
      "mysql": {
        "columnName": "campus_phone",
        "dataType": "varchar",
        "dataLength": 60,
        "dataPrecision": null,
        "dataScale": null,
        "nullable": "Y"
      }
    },
    "campusEmail": {
      "type": "String",
      "required": false,
      "length": 50,
      "precision": null,
      "scale": null,
      "mysql": {
        "columnName": "campus_email",
        "dataType": "varchar",
        "dataLength": 50,
        "dataPrecision": null,
        "dataScale": null,
        "nullable": "Y"
      }
    },
    "campusBiometric": {
      "type": "String",
      "required": false,
      "length": 10,
      "precision": null,
      "scale": null,
      "mysql": {
        "columnName": "campus_biometric",
        "dataType": "varchar",
        "dataLength": 10,
        "dataPrecision": null,
        "dataScale": null,
        "nullable": "Y"
      }
    },
    "inchargePhoto": {
      "type": "String",
      "required": false,
      "length": 50,
      "precision": null,
      "scale": null,
      "mysql": {
        "columnName": "incharge_photo",
        "dataType": "varchar",
        "dataLength": 50,
        "dataPrecision": null,
        "dataScale": null,
        "nullable": "Y"
      }
    },
    "inchargeSignature": {
      "type": "String",
      "required": false,
      "length": 50,
      "precision": null,
      "scale": null,
      "mysql": {
        "columnName": "incharge_signature",
        "dataType": "varchar",
        "dataLength": 50,
        "dataPrecision": null,
        "dataScale": null,
        "nullable": "Y"
      }
    },
    "instId": {
      "type": "Number",
      "required": false,
      "length": null,
      "precision": 10,
      "scale": 0,
      "mysql": {
        "columnName": "inst_id",
        "dataType": "int",
        "dataLength": null,
        "dataPrecision": 10,
        "dataScale": 0,
        "nullable": "Y"
      }
    },
    "remarks": {
      "type": "String",
      "required": false,
      "length": 50,
      "precision": null,
      "scale": null,
      "mysql": {
        "columnName": "remarks",
        "dataType": "varchar",
        "dataLength": 50,
        "dataPrecision": null,
        "dataScale": null,
        "nullable": "Y"
      }
    },
    "campusCode": {
      "type": "String",
      "required": false,
      "length": 2,
      "precision": null,
      "scale": null,
      "mysql": {
        "columnName": "campus_code",
        "dataType": "varchar",
        "dataLength": 2,
        "dataPrecision": null,
        "dataScale": null,
        "nullable": "Y"
      }
    },
    "biometricType": {
      "type": "String",
      "required": false,
      "length": 10,
      "precision": null,
      "scale": null,
      "mysql": {
        "columnName": "biometric_type",
        "dataType": "varchar",
        "dataLength": 10,
        "dataPrecision": null,
        "dataScale": null,
        "nullable": "Y"
      }
    },
    "instname": {
      "type": "String",
      "required": false,
      "length": 50,
      "precision": null,
      "scale": null,
      "mysql": {
        "columnName": "InstName",
        "dataType": "varchar",
        "dataLength": 50,
        "dataPrecision": null,
        "dataScale": null,
        "nullable": "Y"
      }
    }
  },
  "validations": [],
  "relations": {},
  "acls": [],
  "methods": {}
}
