{
  "name": "Vendordetails",
  "options": {
    "idInjection": false,
    "mysql": {
      "schema": "itinfra",
      "table": "vendorDetails"
    }
  },
  "properties": {
    "vcity": {
      "type": "String",
      "required": false,
      "length": 30,
      "precision": null,
      "scale": null,
      "mysql": {
        "columnName": "vcity",
        "dataType": "varchar",
        "dataLength": 30,
        "dataPrecision": null,
        "dataScale": null,
        "nullable": "Y"
      }
    },
    "vemail": {
      "type": "String",
      "required": false,
      "length": 30,
      "precision": null,
      "scale": null,
      "mysql": {
        "columnName": "vemail",
        "dataType": "varchar",
        "dataLength": 30,
        "dataPrecision": null,
        "dataScale": null,
        "nullable": "Y"
      }
    },
    "vid": {
      "type": "Number",
      "required": true,
      "length": null,
      "precision": 10,
      "scale": 0,
      "id": 1,
      "mysql": {
        "columnName": "vid",
        "dataType": "int",
        "dataLength": null,
        "dataPrecision": 10,
        "dataScale": 0,
        "nullable": "N"
      }
    },
    "vname": {
      "type": "String",
      "required": false,
      "length": 30,
      "precision": null,
      "scale": null,
      "mysql": {
        "columnName": "vname",
        "dataType": "varchar",
        "dataLength": 30,
        "dataPrecision": null,
        "dataScale": null,
        "nullable": "Y"
      }
    },
    "vphone": {
      "type": "String",
      "required": false,
      "length": 30,
      "precision": null,
      "scale": null,
      "mysql": {
        "columnName": "vphone",
        "dataType": "varchar",
        "dataLength": 30,
        "dataPrecision": null,
        "dataScale": null,
        "nullable": "Y"
      }
    }
  }
}